[
  {
    "id": 2,
    "name": "54"
  },
  {
    "id": 3,
    "name": "58"
  },
  {
    "id": 4,
    "name": "60"
  },
  {
    "id": 5,
    "name": "70"
  },
  {
    "id": 6,
    "name": "80"
  },
  {
    "id": 7,
    "name": "90"
  },
  {
    "id": 8,
    "name": "100"
  },
  {
    "id": 9,
    "name": "120"
  },
  {
    "id": 10,
    "name": "128"
  },
  {
    "id": 11,
    "name": "170"
  },
  {
    "id": 12,
    "name": "250"
  },
  {
    "id": 13,
    "name": "280"
  },
  {
    "id": 14,
    "name": "290"
  },
  {
    "id": 15,
    "name": "300"
  },
  {
    "id": 16,
    "name": "320"
  },
  {
    "id": 17,
    "name": "330"
  },
  {
    "id": 18,
    "name": "340"
  },
  {
    "id": 19,
    "name": "350"
  },
  {
    "id": 20,
    "name": "75"
  },
  {
    "id": 21,
    "name": "360"
  },
  {
    "id": 22,
    "name": "52"
  },
  {
    "id": 23,
    "name": "40"
  },
  {
    "id": 24,
    "name": "45"
  },
  {
    "id": 25,
    "name": "230"
  },
  {
    "id": 26,
    "name": "0"
  }
]